mylib025/__init__.py
mylib025-0.1.dist-info/LICENSE.txt
mylib025-0.1.dist-info/METADATA
mylib025-0.1.dist-info/WHEEL
mylib025-0.1.dist-info/top_level.txt
mylib025-0.1.dist-info/RECORD
